ispynanoaod/__init__.py
ispynanoaod/core/__init__.py
ispynanoaod/core/data_loader.py
ispynanoaod/core/event_display.py
ispynanoaod/display/__init__.py
ispynanoaod/display/controls.py
ispynanoaod/display/renderer.py
ispynanoaod/objects/__init__.py
ispynanoaod/objects/detector.py
ispynanoaod/objects/objects.py
ispynanoaod-0.1.2.dist-info/licenses/LICENSE
ispynanoaod-0.1.2.dist-info/METADATA
ispynanoaod-0.1.2.dist-info/WHEEL
ispynanoaod-0.1.2.dist-info/top_level.txt
ispynanoaod-0.1.2.dist-info/RECORD
