Metadata-Version: 2.4
Name: ispynanoaod
Version: 0.1.2
Summary: A simple python event display for CMS nanoaod
Author-email: Thomas McCauley <thomas.mccauley@cern.ch>
License: BSD 3-Clause License
Project-URL: Homepage, https://github.com/cms-outreach/ispy-nanoaod
Keywords: visualization,nanoaod,CMS
Requires-Python: >=3.8
License-File: LICENSE
Requires-Dist: pythreejs
Requires-Dist: uproot
Requires-Dist: awkward
Requires-Dist: jupyter
Dynamic: license-file
